{
    "accessory": "DaylightSensors",
    "name":"Tageszeit",
    "port":8081,
    "tickTimer":10000,
    "dayStartsActive":false,
    "trigger":[        
        {
            "active":true,
            "type":"time",
            "value":"6:15"
        },
        {
            "active":false,
            "type":"time",
            "value":"9:00 PM"
        },
        {
            "active":false,
            "type":"altitude",
            "value":"0.03"
        }
    ],
    "location":{
        "longitude":-0.118092,
        "latitude":51.509865
    }
}